fir3base
