Metadata-Version: 1.0
Name: fir3base
Version: 0.6.0
Summary: Some description.
Home-page: http://github.com/vandenberghinc/fir3base
Author: Daan van den Bergh
Author-email: vandenberghinc.contact@gmail.com
License: MIT
Platform: UNKNOWN
